choieojinTest/bmi.py
choieojinTest/test1.py
choieojinTest/test2.py
choieojinTest-0.0.0.3.dist-info/METADATA
choieojinTest-0.0.0.3.dist-info/WHEEL
choieojinTest-0.0.0.3.dist-info/top_level.txt
choieojinTest-0.0.0.3.dist-info/RECORD
