Metadata-Version: 2.1
Name: choieojinTest
Version: 0.0.0.3
Summary: My First Test Package
Home-page: https://blog.naver.com/ji7225
Author: Eojin Choi
Author-email: eojin7225@gmail.com
License: MIT
Platform: UNKNOWN
Requires-Python: >=3
